ee_satellites.py
landsat8.py
sentinel1.py
sentinel2.py
ee_satellites-1.0.0.dist-info/METADATA
ee_satellites-1.0.0.dist-info/WHEEL
ee_satellites-1.0.0.dist-info/top_level.txt
ee_satellites-1.0.0.dist-info/RECORD
