Metadata-Version: 2.1
Name: ee_satellites
Version: 1.0.0
Summary: A Python library that allows to extract data from satellites, exploiting machine parallelism and relying on Google Earth Engine APIs.
Home-page: https://github.com/Amatofrancesco99/ee-satellites
Author: Francesco Amato
Author-email: amatofrancesco99@gmail.com
License: mit
Classifier: Programming Language :: Python :: 3
Classifier: License :: OSI Approved :: MIT License
Classifier: Operating System :: OS Independent
Classifier: Development Status :: 5 - Production/Stable
Classifier: Intended Audience :: Developers
Classifier: Intended Audience :: Science/Research
Classifier: Topic :: Scientific/Engineering
Requires-Dist: earthengine-api
Requires-Dist: pandas
